{
  "features": [
    {
      "geometry": {
        "coordinates": [
          [
            117.575173,
            15.155216
          ],
          [
            117.590966,
            15.196966
          ],
          [
            117.605386,
            15.216182
          ],
          [
            117.615685,
            15.229433
          ],
          [
            117.627358,
            15.243346
          ],
          [
            117.649331,
            15.255932
          ],
          [
            117.668557,
            15.265869
          ],
          [
            117.691216,
            15.273818
          ],
          [
            117.734475,
            15.280442
          ],
          [
            117.766061,
            15.291702
          ]
        ],
        "type": "MultiPoint"
      },
      "properties": {
        "info": {
          "1467520200000": null,
          "1467556200000": null,
          "1467592200000": {
            "国别": "美国",
            "型号": "驱逐舰",
            "异常原因": "轨迹异常",
            "批号": 1
          },
          "1467628200000": null,
          "1467664200000": null,
          "1467700200000": null,
          "1467736200000": null,
          "1467772200000": null,
          "1467808200000": null,
          "1467844200000": null
        },
        "speed": [
          1000,
          1000,
          1000,
          1000,
          1000,
          1000,
          1000,
          1000,
          1000,
          1000
        ],
        "time": [
          1467520200000,
          1467556200000,
          1467592200000,
          1467628200000,
          1467664200000,
          1467700200000,
          1467736200000,
          1467772200000,
          1467808200000,
          1467844200000
        ],
        "title": ""
      },
      "type": "Feature"
    },
    {
      "geometry": {
        "coordinates": [
          [
            117.670617,
            15.044506
          ],
          [
            117.698083,
            15.061746
          ],
          [
            117.722115,
            15.067713
          ],
          [
            117.754388,
            15.07567
          ],
          [
            117.788033,
            15.082963
          ],
          [
            117.822366,
            15.092907
          ],
          [
            117.840905,
            15.112795
          ],
          [
            117.863564,
            15.124727
          ],
          [
            117.876611,
            15.132018
          ],
          [
            117.889657,
            15.148588
          ]
        ],
        "type": "MultiPoint"
      },
      "properties": {
        "info": {
          "1467520200000": null,
          "1467556200000": {
            "国别": "美国",
            "型号": "驱逐舰",
            "异常原因": "轨迹异常",
            "批号": 2
          },
          "1467592200000": null,
          "1467628200000": null,
          "1467664200000": null,
          "1467700200000": null,
          "1467736200000": null,
          "1467772200000": null,
          "1467808200000": null,
          "1467844200000": null
        },
        "speed": [
          1000,
          1000,
          1000,
          1000,
          1000,
          1000,
          1000,
          1000,
          1000,
          1000
        ],
        "time": [
          1467520200000,
          1467556200000,
          1467592200000,
          1467628200000,
          1467664200000,
          1467700200000,
          1467736200000,
          1467772200000,
          1467808200000,
          1467844200000
        ],
        "title": ""
      },
      "type": "Feature"
    },
    {
      "geometry": {
        "coordinates": [
          [
            117.765374,
            15.242021
          ],
          [
            117.761941,
            15.228108
          ],
          [
            117.768807,
            15.216844
          ],
          [
            117.77636,
            15.209556
          ],
          [
            117.78872,
            15.199617
          ],
          [
            117.80108,
            15.187027
          ],
          [
            117.810693,
            15.181062
          ],
          [
            117.825112,
            15.176424
          ],
          [
            117.853951,
            15.165157
          ],
          [
            117.868371,
            15.152565
          ]
        ],
        "type": "MultiPoint"
      },
      "properties": {
        "info": {
          "1467520200000": null,
          "1467556200000": null,
          "1467592200000": null,
          "1467628200000": null,
          "1467664200000": null,
          "1467700200000": null,
          "1467736200000": null,
          "1467772200000": null,
          "1467808200000": null,
          "1467844200000": null
        },
        "speed": [
          1000,
          1000,
          1000,
          1000,
          1000,
          1000,
          1000,
          1000,
          1000,
          1000
        ],
        "time": [
          1467520200000,
          1467556200000,
          1467592200000,
          1467628200000,
          1467664200000,
          1467700200000,
          1467736200000,
          1467772200000,
          1467808200000,
          1467844200000
        ],
        "title": ""
      },
      "type": "Feature"
    },
    {
      "geometry": {
        "coordinates": [
          [
            117.849832,
            15.22877
          ],
          [
            117.852578,
            15.210881
          ],
          [
            117.853265,
            15.194978
          ],
          [
            117.858758,
            15.173773
          ],
          [
            117.856011,
            15.154553
          ],
          [
            117.855325,
            15.138646
          ],
          [
            117.848458,
            15.124727
          ],
          [
            117.848458,
            15.110806
          ],
          [
            117.841592,
            15.094896
          ],
          [
            117.806573,
            15.084951
          ]
        ],
        "type": "MultiPoint"
      },
      "properties": {
        "info": {
          "1467520200000": null,
          "1467556200000": null,
          "1467592200000": null,
          "1467628200000": null,
          "1467664200000": null,
          "1467700200000": null,
          "1467736200000": null,
          "1467772200000": null,
          "1467808200000": null,
          "1467844200000": {
            "国别": "美国",
            "型号": "驱逐舰",
            "异常原因": "轨迹异常",
            "批号": 3
          }
        },
        "speed": [
          1000,
          1000,
          1000,
          1000,
          1000,
          1000,
          1000,
          1000,
          1000,
          1000
        ],
        "time": [
          1467520200000,
          1467556200000,
          1467592200000,
          1467628200000,
          1467664200000,
          1467700200000,
          1467736200000,
          1467772200000,
          1467808200000,
          1467844200000
        ],
        "title": ""
      },
      "type": "Feature"
    },
    {
      "geometry": {
        "coordinates": [
          [
            117.678738,
            14.939048
          ],
          [
            117.686291,
            14.953644
          ],
          [
            117.696591,
            14.971554
          ],
          [
            117.707577,
            14.987474
          ],
          [
            117.717877,
            15.014004
          ],
          [
            117.732296,
            15.035888
          ],
          [
            117.742596,
            15.049151
          ],
          [
            117.761822,
            15.05976
          ],
          [
            117.776928,
            15.069043
          ],
          [
            117.790661,
            15.083629
          ]
        ],
        "type": "MultiPoint"
      },
      "properties": {
        "info": {
          "1467520200000": null,
          "1467556200000": null,
          "1467592200000": null,
          "1467628200000": null,
          "1467664200000": null,
          "1467700200000": null,
          "1467736200000": null,
          "1467772200000": null,
          "1467808200000": null,
          "1467844200000": null
        },
        "speed": [
          1000,
          1000,
          1000,
          1000,
          1000,
          1000,
          1000,
          1000,
          1000,
          1000
        ],
        "time": [
          1467520200000,
          1467556200000,
          1467592200000,
          1467628200000,
          1467664200000,
          1467700200000,
          1467736200000,
          1467772200000,
          1467808200000,
          1467844200000
        ],
        "title": ""
      },
      "type": "Feature"
    }
  ],
  "type": "FeatureCollection"
}